MANIFEST.in
README.rst
package.json
setup.py
itcase_sphinx_theme/.DS_Store
itcase_sphinx_theme/__init__.py
itcase_sphinx_theme/__init__.pyc
itcase_sphinx_theme.egg-info/PKG-INFO
itcase_sphinx_theme.egg-info/SOURCES.txt
itcase_sphinx_theme.egg-info/dependency_links.txt
itcase_sphinx_theme.egg-info/not-zip-safe
itcase_sphinx_theme.egg-info/top_level.txt
itcase_sphinx_theme/__pycache__/__init__.cpython-36.pyc
itcase_sphinx_theme/itcase/.DS_Store
itcase_sphinx_theme/itcase/base.html
itcase_sphinx_theme/itcase/layout.html
itcase_sphinx_theme/itcase/relations.html
itcase_sphinx_theme/itcase/searchbox.html
itcase_sphinx_theme/itcase/theme.conf
itcase_sphinx_theme/itcase/versions.html
itcase_sphinx_theme/itcase/include/breadcrumbs.html
itcase_sphinx_theme/itcase/include/footer.html
itcase_sphinx_theme/itcase/include/search.html
itcase_sphinx_theme/itcase/static/.DS_Store
itcase_sphinx_theme/itcase/static/css/.DS_Store
itcase_sphinx_theme/itcase/static/css/__main.css
itcase_sphinx_theme/itcase/static/css/__main.css.map
itcase_sphinx_theme/itcase/static/css/admonition.css
itcase_sphinx_theme/itcase/static/css/badge.css
itcase_sphinx_theme/itcase/static/css/badge_only.css
itcase_sphinx_theme/itcase/static/css/breakpoints.yml
itcase_sphinx_theme/itcase/static/css/import.css
itcase_sphinx_theme/itcase/static/css/main.css
itcase_sphinx_theme/itcase/static/css/mediaqueries.css
itcase_sphinx_theme/itcase/static/css/settings.css
itcase_sphinx_theme/itcase/static/css/theme.css
itcase_sphinx_theme/itcase/static/css/btn/btn.css
itcase_sphinx_theme/itcase/static/css/codeblock/code-block-caption.css
itcase_sphinx_theme/itcase/static/css/codeblock/codeblock.css
itcase_sphinx_theme/itcase/static/css/codeblock/highlight.css
itcase_sphinx_theme/itcase/static/css/codeblock/highlighttable.css
itcase_sphinx_theme/itcase/static/css/codeblock/literal-block-wrapper.css
itcase_sphinx_theme/itcase/static/css/footer/footer.css
itcase_sphinx_theme/itcase/static/css/menu/menu-mobile.css
itcase_sphinx_theme/itcase/static/css/menu/menu.css
itcase_sphinx_theme/itcase/static/css/nav/nav.css
itcase_sphinx_theme/itcase/static/css/page/page.css
itcase_sphinx_theme/itcase/static/css/page/page_type_main-page.css
