Metadata-Version: 1.1
Name: itcase-sphinx-theme
Version: 0.3.1
Summary: ITCase Sphinx themes for documentation styling.
Home-page: https://github.com/ITCase/itcase_sphinx_theme
Author: ITCase
Author-email: info@itcase.pro
License: UNKNOWN
Keywords: itcase web sphinx documentation
Platform: UNKNOWN
Classifier: Environment :: Web Environment
Classifier: Intended Audience :: Developers
Classifier: Intended Audience :: System Administrators
Classifier: Programming Language :: Python
Classifier: License :: Repoze Public License
Classifier: Topic :: Internet
Classifier: Topic :: Software Development :: Documentation
